LICENSE
README.md
setup.py
start.py
eyes_soatra/__init__.py
eyes_soatra/eyes.py
eyes_soatra.egg-info/PKG-INFO
eyes_soatra.egg-info/SOURCES.txt
eyes_soatra.egg-info/dependency_links.txt
eyes_soatra.egg-info/requires.txt
eyes_soatra.egg-info/top_level.txt
eyes_soatra/constant/__init__.py
eyes_soatra/constant/classes.py
eyes_soatra/constant/labels.py
eyes_soatra/constant/vars.py
eyes_soatra/constant/area/__init__.py
eyes_soatra/constant/area/id.py
eyes_soatra/constant/depends/__init__.py
eyes_soatra/constant/depends/app_date/__init__.py
eyes_soatra/constant/depends/app_date/end.py
eyes_soatra/constant/depends/app_date/period.py
eyes_soatra/constant/depends/app_date/start.py
eyes_soatra/constant/depends/app_date/formats/__init__.py
eyes_soatra/constant/depends/app_date/formats/end.py
eyes_soatra/constant/depends/app_date/formats/period.py
eyes_soatra/constant/depends/app_date/formats/start.py
eyes_soatra/constant/depends/view/__init__.py
eyes_soatra/constant/depends/view/no_data.py
eyes_soatra/constant/depends/view/not_found.py
eyes_soatra/constant/libs/__init__.py
eyes_soatra/constant/libs/requests.py
eyes_soatra/constant/user/__init__.py
eyes_soatra/constant/user/user_agents.py
eyes_soatra/funcs/__init__.py
eyes_soatra/funcs/time_app.py
eyes_soatra/funcs/view_page.py
eyes_soatra/funcs/listener/__init__.py
eyes_soatra/funcs/listener/watch_changes.py
eyes_soatra/funcs/utils/__init__.py
eyes_soatra/funcs/utils/console.py
eyes_soatra/funcs/utils/dict.py
eyes_soatra/funcs/utils/list.py
eyes_soatra/funcs/utils/number.py
eyes_soatra/funcs/utils/string.py
eyes_soatra/funcs/utils/time.py
test/test.py
test/test2.py
test/test3.py