Metadata-Version: 2.1
Name: eyes-soatra
Version: 0.0.33
Summary: Eyes
Author: Soatra
Author-email: johnsoatra@gmail.com
Keywords: python,crawler,scanner,requests
Classifier: Development Status :: 1 - Planning
Classifier: Intended Audience :: Developers
Classifier: Programming Language :: Python :: 3
Classifier: Operating System :: Unix
Classifier: Operating System :: MacOS :: MacOS X
Classifier: Operating System :: Microsoft :: Windows
License-File: LICENSE
